README.md
setup.py
bin/networkml
networkml/NetworkML.py
networkml/algorithms/__init__.py
networkml/algorithms/base.py
networkml/algorithms/sos/SoSmodel.py
networkml/algorithms/sos/__init__.py
networkml/algorithms/sos/eval_SoSModel.py
networkml/algorithms/sos/train_SoSModel.py
networkml/configs/config.json
networkml/configs/label_assignments.json
networkml/parsers/__init__.py
networkml/parsers/netflow/__init__.py
networkml/parsers/pcap/__init__.py
networkml/parsers/pcap/featurizer.py
networkml/parsers/pcap/pcap_utils.py
networkml/parsers/pcap/reader.py
networkml/parsers/pcap/session_iterator.py
networkml/parsers/pcap/session_sequence.py
networkml/utils/__init__.py
networkml/utils/common.py
networkml/utils/model.py
networkml/utils/training_utils.py
poseidonml.egg-info/PKG-INFO
poseidonml.egg-info/SOURCES.txt
poseidonml.egg-info/dependency_links.txt
poseidonml.egg-info/requires.txt
poseidonml.egg-info/top_level.txt