Metadata-Version: 1.2
Name: poseidonml
Version: 0.3.2
Summary: A utility package for extracting and analyzing features in network traffic.
Home-page: https://github.com/CyberReboot/PoseidonML
Author: cglewis
Author-email: clewis@iqt.org
Maintainer: cglewis
Maintainer-email: clewis@iqt.org
License: Apache License 2.0
Keywords: machine learning network analysis utilities
Platform: UNKNOWN
